djoser_web3/__init__.py
djoser_web3/admin.py
djoser_web3/apps.py
djoser_web3/models.py
djoser_web3/serializers.py
djoser_web3/urls.py
djoser_web3/utils.py
djoser_web3/views.py
djoser_web3-0.0.2.dist-info/LICENSE
djoser_web3-0.0.2.dist-info/METADATA
djoser_web3-0.0.2.dist-info/WHEEL
djoser_web3-0.0.2.dist-info/top_level.txt
djoser_web3-0.0.2.dist-info/RECORD
