Metadata-Version: 2.1
Name: djoser-web3
Version: 0.0.2
Summary: Extension of Djoser package that includes Web3 Authentication for Django Rest Framework
Home-page: https://boomslag.com
Author: Boomslag
Author-email: mail@boomslag.com
Maintainer-email: support@boomslag.com
License: MIT
Keywords: djangorestframework web3 ethereum
Classifier: Environment :: Web Environment
Classifier: Framework :: Django
Classifier: Intended Audience :: Developers
Classifier: License :: OSI Approved :: MIT License
Classifier: Operating System :: OS Independent
Classifier: Programming Language :: Python :: 3
Classifier: Programming Language :: Python :: 3.5
Classifier: Programming Language :: Python :: 3.6
Classifier: Programming Language :: Python :: 3.7
Classifier: Programming Language :: Python :: 3.8
Classifier: Programming Language :: Python :: 3.9
Classifier: Topic :: Software Development :: Libraries :: Python Modules
License-File: LICENSE
